{"23300": {"ce": 11390, "pe": 25056, "ce_ltp": 449.9, "pe_ltp": 153.25}, "23350": {"ce": 2758, "pe": 9857, "ce_ltp": 409.85, "pe_ltp": 166.0}, "23400": {"ce": 14788, "pe": 22809, "ce_ltp": 375.35, "pe_ltp": 182.5}, "23450": {"ce": 4334, "pe": 11197, "ce_ltp": 341.1, "pe_ltp": 196.6}, "23500": {"ce": 35536, "pe": 41481, "ce_ltp": 309.35, "pe_ltp": 215.0}, "23550": {"ce": 8811, "pe": 9226, "ce_ltp": 282.5, "pe_ltp": 234.4}, "23600": {"ce": 32696, "pe": 31226, "ce_ltp": 252.0, "pe_ltp": 255.45}, "23650": {"ce": 5742, "pe": 8807, "ce_ltp": 224.4, "pe_ltp": 277.45}, "23700": {"ce": 16683, "pe": 8926, "ce_ltp": 198.0, "pe_ltp": 302.4}, "23750": {"ce": 5397, "pe": 1842, "ce_ltp": 172.1, "pe_ltp": 330.25}, "23800": {"ce": 25059, "pe": 8850, "ce_ltp": 152.0, "pe_ltp": 355.0}, "23850": {"ce": 3799, "pe": 1067, "ce_ltp": 131.9, "pe_ltp": 384.35}}