{"22850": {"ce": 1360, "pe": 8253, "ce_ltp": 397.65, "pe_ltp": 160.6}, "22900": {"ce": 3761, "pe": 22953, "ce_ltp": 368.8, "pe_ltp": 175.85}, "22950": {"ce": 3574, "pe": 10952, "ce_ltp": 335.3, "pe_ltp": 192.75}, "23000": {"ce": 28138, "pe": 83441, "ce_ltp": 303.95, "pe_ltp": 210.5}, "23050": {"ce": 7511, "pe": 13899, "ce_ltp": 274.5, "pe_ltp": 230.2}, "23100": {"ce": 34987, "pe": 42881, "ce_ltp": 245.4, "pe_ltp": 251.65}, "23150": {"ce": 27109, "pe": 21585, "ce_ltp": 218.9, "pe_ltp": 275.1}, "23200": {"ce": 79299, "pe": 52093, "ce_ltp": 193.2, "pe_ltp": 300.5}, "23250": {"ce": 50997, "pe": 23873, "ce_ltp": 170.05, "pe_ltp": 326.45}, "23300": {"ce": 109812, "pe": 51189, "ce_ltp": 148.8, "pe_ltp": 355.6}, "23350": {"ce": 37108, "pe": 11073, "ce_ltp": 129.55, "pe_ltp": 385.65}, "23400": {"ce": 63096, "pe": 21477, "ce_ltp": 112.15, "pe_ltp": 417.95}}