{"23150": {"ce": 17309, "pe": 109580, "ce_ltp": 297.7, "pe_ltp": 3.1}, "23200": {"ce": 27369, "pe": 217636, "ce_ltp": 251.35, "pe_ltp": 4.6}, "23250": {"ce": 17330, "pe": 175538, "ce_ltp": 204.5, "pe_ltp": 7.3}, "23300": {"ce": 52044, "pe": 267547, "ce_ltp": 158.85, "pe_ltp": 12.7}, "23350": {"ce": 71019, "pe": 210150, "ce_ltp": 119.15, "pe_ltp": 21.4}, "23400": {"ce": 240308, "pe": 298992, "ce_ltp": 83.15, "pe_ltp": 36.4}, "23450": {"ce": 210480, "pe": 110223, "ce_ltp": 54.9, "pe_ltp": 57.4}, "23500": {"ce": 454516, "pe": 109505, "ce_ltp": 34.0, "pe_ltp": 87.3}, "23550": {"ce": 276223, "pe": 38338, "ce_ltp": 19.7, "pe_ltp": 122.8}, "23600": {"ce": 304586, "pe": 30105, "ce_ltp": 11.2, "pe_ltp": 163.95}, "23650": {"ce": 189211, "pe": 7730, "ce_ltp": 6.25, "pe_ltp": 209.0}, "23700": {"ce": 214886, "pe": 14344, "ce_ltp": 3.55, "pe_ltp": 257.1}}