{"24400": {"ce": 2587, "pe": 144013, "ce_ltp": 282.95, "pe_ltp": 4.0}, "24450": {"ce": 1055, "pe": 105560, "ce_ltp": 235.8, "pe_ltp": 6.2}, "24500": {"ce": 20719, "pe": 366677, "ce_ltp": 189.25, "pe_ltp": 10.05}, "24550": {"ce": 8224, "pe": 141110, "ce_ltp": 145.45, "pe_ltp": 16.35}, "24600": {"ce": 46522, "pe": 302146, "ce_ltp": 105.95, "pe_ltp": 26.9}, "24650": {"ce": 64075, "pe": 253425, "ce_ltp": 71.4, "pe_ltp": 42.85}, "24700": {"ce": 256610, "pe": 339540, "ce_ltp": 44.25, "pe_ltp": 65.85}, "24750": {"ce": 262429, "pe": 137654, "ce_ltp": 24.35, "pe_ltp": 96.1}, "24800": {"ce": 452060, "pe": 146705, "ce_ltp": 12.1, "pe_ltp": 133.5}, "24850": {"ce": 245032, "pe": 58890, "ce_ltp": 6.3, "pe_ltp": 176.5}, "24900": {"ce": 298285, "pe": 82586, "ce_ltp": 3.55, "pe_ltp": 224.0}, "24950": {"ce": 136620, "pe": 27698, "ce_ltp": 2.3, "pe_ltp": 271.75}}